bondzai_gateway-0.0.31-py3.11-nspkg.pth
bondzai/gateway/__init__.py
bondzai/gateway/config.yml
bondzai/gateway/core/application.py
bondzai/gateway/core/device.py
bondzai/gateway/core/events.py
bondzai/gateway/core/fsm.py
bondzai/gateway/core/logger.py
bondzai/gateway/core/manager.py
bondzai/gateway/core/observer.py
bondzai/gateway/core/packets_handler.py
bondzai/gateway/core/message/base.py
bondzai/gateway/core/message/command.py
bondzai/gateway/core/message/enums.py
bondzai/gateway/core/message/event.py
bondzai/gateway/core/message/payload.py
bondzai/gateway/core/message/process_dbm.py
bondzai/gateway/core/message/response.py
bondzai/gateway/core/message/utils.py
bondzai/gateway/core/websocket/client.py
bondzai/gateway/core/websocket/connector.py
bondzai/gateway/core/websocket/request.py
bondzai/gateway/core/websocket/utils.py
bondzai/gateway/device_connectors/base.py
bondzai/gateway/device_connectors/serial.py
bondzai/gateway/device_connectors/socket_server.py
tests/__init__.py
tests/test_observer.py
bondzai_gateway-0.0.31.dist-info/METADATA
bondzai_gateway-0.0.31.dist-info/NOTICE
bondzai_gateway-0.0.31.dist-info/WHEEL
bondzai_gateway-0.0.31.dist-info/entry_points.txt
bondzai_gateway-0.0.31.dist-info/namespace_packages.txt
bondzai_gateway-0.0.31.dist-info/top_level.txt
bondzai_gateway-0.0.31.dist-info/zip-safe
bondzai_gateway-0.0.31.dist-info/RECORD
